groundsman/__init__.py
groundsman-0.0.1.dist-info/METADATA
groundsman-0.0.1.dist-info/WHEEL
groundsman-0.0.1.dist-info/entry_points.txt
groundsman-0.0.1.dist-info/top_level.txt
groundsman-0.0.1.dist-info/RECORD
