Metadata-Version: 2.4
Name: groundsman
Version: 0.0.1
Summary: Add your description here
Requires-Python: >=3.12
Requires-Dist: axis-vapix>=0.1.5
Requires-Dist: dotenv>=0.9.9
Requires-Dist: logging>=0.4.9.6
Requires-Dist: pco-calendar>=0.1.2
Requires-Dist: pyyaml>=6.0.2
Requires-Dist: schedule>=1.2.2
